{
  "vertical": "tutor-math",
  "hebrewName": "מורה פרטי — מתמטיקה",
  "cluster": "education",
  "tier": "A",
  "examples": [
    {
      "archetype": "A",
      "persona": "אורית שמואל",
      "lp": {
        "heroHeadline": "הילד נכשל בבגרות במתמטיקה? עולים ציון ונרגעים",
        "heroSubheadline": "אם אתה בלחץ מהמועד הקרוב, אורית שמואל תזהה איפה הילד נתקע ותבנה לו בסיס, שיטה וביטחון. 12 שנות ניסיון, תואר ראשון במתמטיקה, התמחות ב-5 יחידות ויותר מ-90% מהתלמידים שלה עוברים.",
        "heroCta": "התקשר עכשיו",
        "trustBarItems": [
          "12 שנות ניסיון",
          "תואר ראשון במתמטיקה",
          "מומחית לבגרות 5 יחידות",
          "90%+ מהתלמידים עוברים"
        ],
        "aboutBlurb": "שמי אורית, מורה פרטית למתמטיקה בפתח תקווה כבר 12 שנה, עם תואר ראשון במתמטיקה והתמחות בבגרות 5 יחידות. אני לא רצה לפי הספר — אני מזהה בדיוק איפה התלמיד נתקע ומפרקת את החומר לצעדים קטנים וברורים. כשאתה מתקשר אליי, אתה מקבל אבחון ישר, תוכנית עבודה ושיעור שמחזיר לילד ביטחון. בסוף, גם הציון עולה וגם הבית נרגע.",
        "servicesHeadline": "מה לומדים איתי",
        "serviceItems": [
          "בגרות במתמטיקה 3–5 יחידות",
          "הכנה לפסיכומטרי עם שיטה ותרגול",
          "שיעורי מתמטיקה לבית ספר יסודי והשלמת פערים"
        ],
        "faqHeadline": "שאלות לפני שמתחילים",
        "faqItems": [
          {
            "q": "הילד בפער גדול. יש טעם להתחיל עכשיו?",
            "a": "כן. מתחילים מהמקום שלו, סוגרים חורים בסיסיים ומתקדמים צעד צעד."
          },
          {
            "q": "את עובדת גם עם 3 יחידות וגם עם 5?",
            "a": "כן. אני מלמדת 3 עד 5 יחידות, עם התמחות בבגרות 5 יחידות."
          },
          {
            "q": "הוא נלחץ וננעל במבחנים. את עובדת גם על זה?",
            "a": "כן. כשיש סדר והבנה, הביטחון חוזר והוא מפסיק להילחץ מכל שאלה."
          },
          {
            "q": "מה קורה אם לא עלינו ציון?",
            "a": "אם לא עלית ציון — השיעורים הבאים חינם."
          }
        ],
        "guaranteeBlock": "אני עומדת מאחורי העבודה שלי: אם לא עלית ציון — השיעורים הבאים חינם.",
        "reviewFeatured": "בנו קיבל 91 בבגרות. אורית מופלאה.",
        "reviewContext": "5 כוכבים בגוגל",
        "responseTimeBadge": null,
        "scarcityLine": null,
        "formHeadline": "ספר לי איפה הילד נתקע, ונבנה לו דרך ברורה",
        "stickyBarLine": "הילד תקוע במתמטיקה? שלח ווצאפ או התקשר"
      }
    },
    {
      "archetype": "B",
      "persona": "רועי לוינזון",
      "lp": {
        "heroHeadline": "הילד שונא מתמטיקה ואין לו בסיס? יש דרך להחזיר לו ביטחון",
        "heroSubheadline": "אם אתה רואה אותו מתייאש מכל תרגיל, נתחיל מהבסיס ונבנה הבנה אמיתית בחשבון, אלגברה, גיאומטריה וטריגונומטריה. שיעור ניסיון חינם בנס ציונה.",
        "heroCta": "התקשר עכשיו",
        "trustBarItems": [
          "7 שנות ניסיון",
          "הנדסאי ומורה מוסמך",
          "הסברים מחיי היומיום",
          "שיעור ניסיון חינם"
        ],
        "aboutBlurb": "שמי רועי, הנדסאי ומורה מוסמך עם 7 שנות ניסיון בלימוד מתמטיקה לתלמידים שאיבדו את הבסיס. אני מלמד דרך דוגמאות מחיי היומיום, כדי שהחומר ירגיש ברור ולא מאיים. כשתתקשר, נבין יחד איפה הילד נתקע ואגיד לך ישר מאיפה מתחילים. אני אוהב לראות את הרגע שבו האסימון נופל והביטחון חוזר.",
        "servicesHeadline": "מה אני מלמד",
        "serviceItems": [
          "חשבון וחיזוק בסיס",
          "אלגברה וגיאומטריה בלי בלבול",
          "טריגונומטריה והכנה למבחנים"
        ],
        "faqHeadline": "שאלות שבדרך כלל שואלים אותי",
        "faqItems": [
          {
            "q": "הבן שלי ממש שונא מתמטיקה. יש מה לעשות?",
            "a": "כן. מתחילים מהבסיס, בקצב שלו, ומחזירים תחושת הצלחה כבר מהשיעורים הראשונים."
          },
          {
            "q": "אתה עובד גם עם תלמידים בלי בסיס בכלל?",
            "a": "כן. אני מסדר איתו את היסודות ואז מתקדם לחומר של הכיתה בלי לקפוץ שלבים."
          },
          {
            "q": "מה קורה בשיעור הראשון?",
            "a": "בודקים איפה הוא נתקע, מגדירים מטרה, ואתה מקבל תמונה ברורה בלי ניחושים."
          },
          {
            "q": "צריך להתחייב מראש לכמה שיעורים?",
            "a": "לא. מתחילים בשיעור ניסיון חינם, ורק אם יש חיבור והתקדמות ממשיכים."
          }
        ],
        "guaranteeBlock": "שיעור ניסיון חינם — אתה רואה אם יש חיבור ואם השיטה שלי מתאימה לילד, בלי לחץ ובלי התחייבות.",
        "reviewFeatured": "בת שלי עברה מ-55 ל-82 תוך 3 חודשים.",
        "reviewContext": "5 כוכבים בגוגל",
        "responseTimeBadge": null,
        "scarcityLine": null,
        "formHeadline": "דבר איתי בטלפון או בווטסאפ ונבין מאיפה מתחילים",
        "stickyBarLine": "שיעור ניסיון חינם — התקשר עכשיו"
      }
    }
  ],
  "generatedAt": "2026-07-02T09:57:49.727Z"
}