{
  "site": "https://www.ajudaica.com/",
  "generatedAt": "2026-07-05T05:25:34.559Z",
  "period": {
    "startDate": "2026-04-06",
    "endDate": "2026-07-05",
    "days": 90
  },
  "totalInRange": 1602,
  "opportunities": [
    {
      "rank": 1,
      "query": "tallit",
      "rankingUrl": "https://www.ajudaica.com/category/4/Tallit/",
      "implementationMode": "create",
      "position": 11.1,
      "impressions": 14958,
      "clicks": 31,
      "ctr": 0.2,
      "score": 222307,
      "intentScore": null,
      "intentFlag": null,
      "intentReason": null,
      "priority": "LOW",
      "actionType": "faq_block"
    },
    {
      "rank": 2,
      "query": "buy sukkot",
      "rankingUrl": "https://www.ajudaica.com/category/388/Sukkot/",
      "implementationMode": "create",
      "position": 9,
      "impressions": 13004,
      "clicks": 0,
      "ctr": 0,
      "score": 221326,
      "intentScore": null,
      "intentFlag": null,
      "intentReason": null,
      "priority": "MEDIUM",
      "actionType": "faq_block"
    },
    {
      "rank": 3,
      "query": "star of david",
      "rankingUrl": "https://www.ajudaica.com/judaica101/star-of-david-meaning-complete-guide/",
      "implementationMode": "enhance",
      "position": 5.2,
      "impressions": 10337,
      "clicks": 1,
      "ctr": 0,
      "score": 215134,
      "intentScore": null,
      "intentFlag": null,
      "intentReason": null,
      "priority": "HIGH",
      "actionType": "faq_block",
      "cannibalFlag": "REVIEW",
      "cannibalReasons": [
        "MULTI_URL"
      ],
      "cannibalUrls": [
        {
          "url": "https://www.ajudaica.com/judaica101/star-of-david/",
          "impressions": 2922,
          "position": 1.3
        }
      ]
    },
    {
      "rank": 4,
      "query": "apropo",
      "rankingUrl": "https://www.ajudaica.com/Apropo-Cone-Shaped-Corn-Snack-by-Osem-Medium/item17409",
      "implementationMode": "enhance",
      "position": 10.4,
      "impressions": 12770,
      "clicks": 0,
      "ctr": 0,
      "score": 199062,
      "intentScore": null,
      "intentFlag": null,
      "intentReason": null,
      "priority": "LOW",
      "actionType": "faq_block"
    },
    {
      "rank": 5,
      "query": "judaica",
      "rankingUrl": "https://www.ajudaica.com/",
      "implementationMode": "create",
      "position": 8.8,
      "impressions": 9922,
      "clicks": 58,
      "ctr": 0.6,
      "score": 170340,
      "intentScore": null,
      "intentFlag": null,
      "intentReason": null,
      "priority": "MEDIUM",
      "actionType": "faq_block"
    },
    {
      "rank": 6,
      "query": "shofar horn",
      "rankingUrl": "https://www.ajudaica.com/category/128/Shofar/",
      "implementationMode": "create",
      "position": 8.3,
      "impressions": 9255,
      "clicks": 41,
      "ctr": 0.4,
      "score": 163969,
      "intentScore": null,
      "intentFlag": null,
      "intentReason": null,
      "priority": "MEDIUM",
      "actionType": "faq_block"
    },
    {
      "rank": 7,
      "query": "jewish prayer shawl",
      "rankingUrl": "https://www.ajudaica.com/category/4/Tallit/",
      "implementationMode": "create",
      "position": 4.7,
      "impressions": 6802,
      "clicks": 1,
      "ctr": 0,
      "score": 145116,
      "intentScore": null,
      "intentFlag": null,
      "intentReason": null,
      "priority": "HIGH",
      "actionType": "faq_block"
    },
    {
      "rank": 8,
      "query": "judaica gifts from israel",
      "rankingUrl": "https://www.ajudaica.com/",
      "implementationMode": "create",
      "position": 6.6,
      "impressions": 6544,
      "clicks": 3,
      "ctr": 0,
      "score": 126681,
      "intentScore": null,
      "intentFlag": null,
      "intentReason": null,
      "priority": "MEDIUM",
      "actionType": "faq_block"
    },
    {
      "rank": 9,
      "query": "kippah",
      "rankingUrl": "https://www.ajudaica.com/category/22/Kippot/",
      "implementationMode": "create",
      "position": 10.6,
      "impressions": 5926,
      "clicks": 7,
      "ctr": 0.1,
      "score": 91464,
      "intentScore": null,
      "intentFlag": null,
      "intentReason": null,
      "priority": "LOW",
      "actionType": "faq_block"
    },
    {
      "rank": 10,
      "query": "tefillin",
      "rankingUrl": "https://www.ajudaica.com/category/3/Tefillin/",
      "implementationMode": "create",
      "position": 12.1,
      "impressions": 6344,
      "clicks": 14,
      "ctr": 0.2,
      "score": 87902,
      "intentScore": null,
      "intentFlag": null,
      "intentReason": null,
      "priority": "LOW",
      "actionType": "faq_block"
    },
    {
      "rank": 11,
      "query": "judaica store",
      "rankingUrl": "https://www.ajudaica.com/",
      "implementationMode": "create",
      "position": 5.7,
      "impressions": 4216,
      "clicks": 69,
      "ctr": 1.6,
      "score": 85674,
      "intentScore": null,
      "intentFlag": null,
      "intentReason": null,
      "priority": "HIGH",
      "actionType": "faq_block",
      "cannibalFlag": "REVIEW",
      "cannibalReasons": [
        "MULTI_URL"
      ],
      "cannibalUrls": [
        {
          "url": "https://www.ajudaica.com/category/412/Judaica-Kids/",
          "impressions": 3281,
          "position": 4.8
        }
      ]
    },
    {
      "rank": 12,
      "query": "dreidel",
      "rankingUrl": "https://www.ajudaica.com/category/106/Dreidels/",
      "implementationMode": "create",
      "position": 13.7,
      "impressions": 6918,
      "clicks": 1,
      "ctr": 0,
      "score": 85247,
      "intentScore": null,
      "intentFlag": null,
      "intentReason": null,
      "priority": "LOW",
      "actionType": "faq_block"
    },
    {
      "rank": 13,
      "query": "judaica store",
      "rankingUrl": "https://www.ajudaica.com/category/412/Judaica-Kids/",
      "implementationMode": "create",
      "position": 4.8,
      "impressions": 3281,
      "clicks": 1,
      "ctr": 0,
      "score": 69529,
      "intentScore": null,
      "intentFlag": null,
      "intentReason": null,
      "priority": "HIGH",
      "actionType": "faq_block",
      "cannibalFlag": "REVIEW",
      "cannibalReasons": [
        "MULTI_URL"
      ],
      "cannibalUrls": [
        {
          "url": "https://www.ajudaica.com/",
          "impressions": 4216,
          "position": 5.7
        }
      ]
    },
    {
      "rank": 14,
      "query": "double star of david",
      "rankingUrl": "https://www.ajudaica.com/Sterling-Silver-Pendant-Necklace-Double-Star-of-David-Outline/item22625",
      "implementationMode": "enhance",
      "position": 4.4,
      "impressions": 3187,
      "clicks": 0,
      "ctr": 0,
      "score": 68916,
      "intentScore": null,
      "intentFlag": null,
      "intentReason": null,
      "priority": "HIGH",
      "actionType": "faq_block",
      "cannibalFlag": "REVIEW",
      "cannibalReasons": [
        "MULTI_URL"
      ],
      "cannibalUrls": [
        {
          "url": "https://www.ajudaica.com/Rhodium-Two-tone-2-Layer-Star-of-David-Necklace/item17420",
          "impressions": 257,
          "position": 11
        }
      ]
    },
    {
      "rank": 15,
      "query": "tallit katan",
      "rankingUrl": "https://www.ajudaica.com/category/45/Tallit-Katan/",
      "implementationMode": "create",
      "position": 4.3,
      "impressions": 2541,
      "clicks": 27,
      "ctr": 1.1,
      "score": 55197,
      "intentScore": null,
      "intentFlag": null,
      "intentReason": null,
      "priority": "HIGH",
      "actionType": "faq_block"
    },
    {
      "rank": 16,
      "query": "shofar",
      "rankingUrl": "https://www.ajudaica.com/category/128/Shofar/",
      "implementationMode": "create",
      "position": 12.3,
      "impressions": 3689,
      "clicks": 7,
      "ctr": 0.2,
      "score": 50530,
      "intentScore": null,
      "intentFlag": null,
      "intentReason": null,
      "priority": "LOW",
      "actionType": "faq_block"
    },
    {
      "rank": 17,
      "query": "tefilin",
      "rankingUrl": "https://www.ajudaica.com/category/3/Tefillin/",
      "implementationMode": "create",
      "position": 8.5,
      "impressions": 2546,
      "clicks": 10,
      "ctr": 0.4,
      "score": 44446,
      "intentScore": null,
      "intentFlag": null,
      "intentReason": null,
      "priority": "MEDIUM",
      "actionType": "faq_block"
    },
    {
      "rank": 18,
      "query": "judaica web store",
      "rankingUrl": "https://www.ajudaica.com/",
      "implementationMode": "create",
      "position": 6.1,
      "impressions": 1857,
      "clicks": 11,
      "ctr": 0.6,
      "score": 36956,
      "intentScore": null,
      "intentFlag": null,
      "intentReason": null,
      "priority": "MEDIUM",
      "actionType": "faq_block"
    },
    {
      "rank": 19,
      "query": "talit",
      "rankingUrl": "https://www.ajudaica.com/Noy-Talit/item268",
      "implementationMode": "enhance",
      "position": 10.8,
      "impressions": 2323,
      "clicks": 2,
      "ctr": 0.1,
      "score": 35283,
      "intentScore": null,
      "intentFlag": null,
      "intentReason": null,
      "priority": "LOW",
      "actionType": "faq_block"
    },
    {
      "rank": 20,
      "query": "jewish candle",
      "rankingUrl": "https://www.ajudaica.com/category/158/Candles/",
      "implementationMode": "create",
      "position": 11.3,
      "impressions": 2204,
      "clicks": 1,
      "ctr": 0,
      "score": 32506,
      "intentScore": null,
      "intentFlag": null,
      "intentReason": null,
      "priority": "LOW",
      "actionType": "faq_block"
    }
  ]
}