{
  "vertical": "laser-hair-removal",
  "hebrewName": "הסרת שיער בלייזר",
  "cluster": "aesthetics",
  "tier": "B",
  "examples": [
    {
      "archetype": "A",
      "persona": "ד\"ר ירדן שגב",
      "lp": {
        "heroHeadline": "מפחד מכאב וכוויות? אפשר להסיר שיער כמעט בלי כאב וברוגע",
        "heroSubheadline": "ד\"ר ירדן שגב, רופאת עור מוסמכת בתל אביב, מטפלת עם אלמה סופרנו בסדרה של 8 טיפולים לתוצאה לצמיתות. אפשר להתחיל בניסיון אזור קטן ראשון ב-200 ש\"ח.",
        "heroCta": "התקשר עכשיו",
        "trustBarItems": [
          "ד\"ר ירדן שגב, רופאת עור מוסמכת",
          "10 שנות ניסיון",
          "אלמה סופרנו",
          "ניסיון אזור קטן ראשון ב-200 ש\"ח"
        ],
        "aboutBlurb": "שמי ירדן, אני רופאת עור מוסמכת עם 10 שנות ניסיון בהסרת שיער בלייזר. אני עובדת עם אלמה סופרנו ובונה סדרת 8 טיפולים מדויקת לפי העור והשיער שלך, בלי למהר ובלי לנחש. כשתתקשר תקבל ממני בדיקה קצרה, הסבר ישר וניסיון אזור קטן ב-200 ש\"ח. אני מאמינה שטיפול טוב מתחיל ברוגע.",
        "servicesHeadline": "הטיפולים בקליניקה",
        "serviceItems": [
          "הסרת שיער בלייזר",
          "איי פי אל וקרוטי-גלים",
          "טיפולי פנים"
        ],
        "faqHeadline": "שאלות ששואלים לפני שמתקשרים",
        "faqItems": [
          {
            "q": "זה כואב?",
            "a": "ברוב האזורים התחושה קלה בהרבה ממה שחשבת. אפשר להתחיל באזור קטן ולבדוק בעצמך."
          },
          {
            "q": "יש סיכון לכוויות?",
            "a": "מתאימים את הטיפול לעור ולשיער שלך ועובדים עם אלמה סופרנו, וזה מוריד מאוד את הסיכון."
          },
          {
            "q": "כמה טיפולים צריך?",
            "a": "ברוב המקרים בונים סדרה של 8 טיפולים. כבר מההתחלה רואים דילול והאטה בצמיחה."
          },
          {
            "q": "איך אדע אם זה מתאים לי?",
            "a": "בשיחה קצרה אני בודקת איתך אזור, עור ושיער ונותנת תשובה ישרה. אם לא מתאים, אגיד לך."
          }
        ],
        "guaranteeBlock": "לא חייב לקפוץ ישר לסדרה מלאה. אפשר להתחיל בניסיון אזור קטן ראשון ב-200 ש\"ח, להרגיש בעצמך ואז להחליט רגוע.",
        "reviewFeatured": "כמעט ללא כאב וללא שיקום. תוצאה מושלמת.",
        "reviewContext": "5 כוכבים בגוגל",
        "responseTimeBadge": null,
        "scarcityLine": null,
        "formHeadline": "דבר איתי בטלפון או בווצאפ ונבדוק מה מתאים לך",
        "stickyBarLine": "מפחד מכאב וכוויות? דבר איתי עכשיו"
      }
    },
    {
      "archetype": "B",
      "persona": "מוריה דרומי",
      "lp": {
        "heroHeadline": "משלם הרבה ולא רואה תוצאה? פה אתה מתקדם עד אפס שיער",
        "heroSubheadline": "בביוטי-לייזר בחיפה אתה מקבל חבילה שנתית ג\"מ בלי הגבלת טיפולים, ועד אפס שיער או שממשיכים חינם.",
        "heroCta": "התקשר עכשיו",
        "trustBarItems": [
          "7 שנות ניסיון",
          "קוסמטיקאית רפואית",
          "חבילה שנתית ג\"מ בלי הגבלת טיפולים",
          "עד אפס שיער או ממשיכים חינם"
        ],
        "aboutBlurb": "שמי מוריה, קוסמטיקאית רפואית עם 7 שנות ניסיון בהסרת שיער בלייזר. אני עובדת בתוכנית שנתית בלי להגביל אותך במספר הטיפולים, כדי שלא תשלם שוב ושוב בלי סוף. כשאתה מתקשר אליי, אני בודקת התאמה ובונה לך מסלול ברור עד אפס שיער. חשוב לי שתרגיש רגוע ושתדע בדיוק איפה אתה עומד.",
        "servicesHeadline": "טיפולים בקליניקה",
        "serviceItems": [
          "הסרת שיער בלייזר",
          "טיפולי פיגמנטציה ועור",
          "טיפול בוורידים"
        ],
        "faqHeadline": "שאלות שכדאי לשאול לפני שמתחילים",
        "faqItems": [
          {
            "q": "תוך כמה טיפולים רואים שינוי?",
            "a": "כבר מהטיפולים הראשונים רואים דילול. הקצב תלוי באזור, בסוג השיער ובהתמדה שלך."
          },
          {
            "q": "מה קורה אם נשאר שיער אחרי החבילה?",
            "a": "ממשיכים חינם עד אפס שיער, לפי ההתחייבות של החבילה השנתית."
          },
          {
            "q": "הטיפול כואב?",
            "a": "מרגישים חום או עקצוץ קצר. אני מתאימה את העוצמה לאזור ולקצב שלך."
          },
          {
            "q": "אפשר לדבר איתך גם בווצאפ?",
            "a": "כן. אפשר להתקשר או לשלוח ווצאפ ולקבל ממני מענה אישי."
          }
        ],
        "guaranteeBlock": "אתה לא נשאר עם הבטחות באוויר. המטרה ברורה: עד אפס שיער, ואם צריך ממשיכים חינם.",
        "reviewFeatured": "חבילה שנתית, שיער אפס אחרי 7 טיפולים.",
        "reviewContext": "5 כוכבים בגוגל",
        "responseTimeBadge": null,
        "scarcityLine": null,
        "formHeadline": "השאר פרטים ואחזור אליך אישית",
        "stickyBarLine": "רוצה לבדוק התאמה? התקשר או שלח ווצאפ"
      }
    }
  ],
  "generatedAt": "2026-07-02T14:38:33.361Z"
}